[{"code": 2562256, "event": 37, "finished": false, "finished_provisional": false, "id": 361, "kickoff_time": "2026-05-17T14:00:00Z", "minutes": 0, "provisional_start_time": false, "started": false, "team_a": 3, "team_a_score": null, "team_h": 1, "team_h_score": null, "stats": [], "team_h_difficulty": 2, "team_a_difficulty": 4, "pulse_id": 125151}, {"code": 2562257, "event": 37, "finished": false, "finished_provisional": false, "id": 362, "kickoff_time": "2026-05-17T14:00:00Z", "minutes": 0, "provisional_start_time": false, "started": false, "team_a": 12, "team_a_score": null, "team_h": 2, "team_h_score": null, "stats": [], "team_h_difficulty": 4, "team_a_difficulty": 4, "pulse_id": 125152}, {"code": 2562255, "event": 37, "finished": false, "finished_provisional": false, "id": 363, "kickoff_time": "2026-05-17T14:00:00Z", "minutes": 0, "provisional_start_time": false, "started": false, "team_a": 13, "team_a_score": null, "team_h": 4, "team_h_score": null, "stats": [], "team_h_difficulty": 4, "team_a_difficulty": 3, "pulse_id": 125153}, {"code": 2562258, "event": 37, "finished": false, "finished_provisional": false, "id": 364, "kickoff_time": "2026-05-17T14:00:00Z", "minutes": 0, "provisional_start_time": false, "started": false, "team_a": 8, "team_a_score": null, "team_h": 5, "team_h_score": null, "stats": [], "team_h_difficulty": 3, "team_a_difficulty": 3, "pulse_id": 125154}, {"code": 2562259, "event": 37, "finished": false, "finished_provisional": false, "id": 365, "kickoff_time": "2026-05-17T14:00:00Z", "minutes": 0, "provisional_start_time": false, "started": false, "team_a": 18, "team_a_score": null, "team_h": 7, "team_h_score": null, "stats": [], "team_h_difficulty": 3, "team_a_difficulty": 4, "pulse_id": 125155}, {"code": 2562260, "event": 37, "finished": false, "finished_provisional": false, "id": 366, "kickoff_time": "2026-05-17T14:00:00Z", "minutes": 0, "provisional_start_time": false, "started": false, "team_a": 17, "team_a_score": null, "team_h": 9, "team_h_score": null, "stats": [], "team_h_difficulty": 2, "team_a_difficulty": 3, "pulse_id": 125156}, {"code": 2562261, "event": 37, "finished": false, "finished_provisional": false, "id": 367, "kickoff_time": "2026-05-17T14:00:00Z", "minutes": 0, "provisional_start_time": false, "started": false, "team_a": 6, "team_a_score": null, "team_h": 11, "team_h_score": null, "stats": [], "team_h_difficulty": 3, "team_a_difficulty": 2, "pulse_id": 125157}, {"code": 2562262, "event": 37, "finished": false, "finished_provisional": false, "id": 368, "kickoff_time": "2026-05-17T14:00:00Z", "minutes": 0, "provisional_start_time": false, "started": false, "team_a": 16, "team_a_score": null, "team_h": 14, "team_h_score": null, "stats": [], "team_h_difficulty": 3, "team_a_difficulty": 3, "pulse_id": 125158}, {"code": 2562263, "event": 37, "finished": false, "finished_provisional": false, "id": 369, "kickoff_time": "2026-05-17T14:00:00Z", "minutes": 0, "provisional_start_time": false, "started": false, "team_a": 19, "team_a_score": null, "team_h": 15, "team_h_score": null, "stats": [], "team_h_difficulty": 2, "team_a_difficulty": 4, "pulse_id": 125159}, {"code": 2562264, "event": 37, "finished": false, "finished_provisional": false, "id": 370, "kickoff_time": "2026-05-17T14:00:00Z", "minutes": 0, "provisional_start_time": false, "started": false, "team_a": 10, "team_a_score": null, "team_h": 20, "team_h_score": null, "stats": [], "team_h_difficulty": 3, "team_a_difficulty": 3, "pulse_id": 125160}]